README.md
setup.cfg
setup.py
src/ApiLeagueOfLegends.egg-info/PKG-INFO
src/ApiLeagueOfLegends.egg-info/SOURCES.txt
src/ApiLeagueOfLegends.egg-info/dependency_links.txt
src/ApiLeagueOfLegends.egg-info/not-zip-safe
src/ApiLeagueOfLegends.egg-info/requires.txt
src/ApiLeagueOfLegends.egg-info/top_level.txt
src/league_of_legends_api/__init__.py
src/league_of_legends_api/test.py
src/league_of_legends_api/Api/__init__.py
src/league_of_legends_api/Api/leaugue_api.py
src/league_of_legends_api/Database/__init__.py
src/league_of_legends_api/Database/database.py
src/league_of_legends_api/Database/objects.py
src/league_of_legends_api/Tools/__init__.py
src/league_of_legends_api/Tools/leaugue_request.py
src/league_of_legends_api/Api/__init__.py
src/league_of_legends_api/Api/leaugue_api.py
src/league_of_legends_api/Database/__init__.py
src/league_of_legends_api/Database/database.py
src/league_of_legends_api/Database/objects.py
src/league_of_legends_api/Tools/__init__.py
src/league_of_legends_api/Tools/leaugue_request.py